autosbatch/__init__.py
autosbatch/autosbatch.py
autosbatch/cli.py
autosbatch/template/CPU_MPI.j2
autosbatch/template/CPU_OpenMP.j2
autosbatch-0.2.7.dist-info/LICENSE
autosbatch-0.2.7.dist-info/METADATA
autosbatch-0.2.7.dist-info/WHEEL
autosbatch-0.2.7.dist-info/entry_points.txt
autosbatch-0.2.7.dist-info/RECORD
