Metadata-Version: 2.1
Name: autosbatch
Version: 0.2.7
Summary: submit hundreds of jobs to slurm automatically.
Home-page: https://github.com/Jianhua-Wang/autosbatch
License: MIT
Author: Jianhua Wang
Author-email: jianhua.mert@gmail.com
Requires-Python: >=3.8,<3.12
Classifier: Development Status :: 2 - Pre-Alpha
Classifier: Intended Audience :: Developers
Classifier: License :: OSI Approved :: MIT License
Classifier: Natural Language :: English
Classifier: Programming Language :: Python :: 3
Classifier: Programming Language :: Python :: 3.8
Classifier: Programming Language :: Python :: 3.9
Classifier: Programming Language :: Python :: 3.10
Classifier: Programming Language :: Python :: 3.11
Classifier: Programming Language :: Python :: 3.7
Requires-Dist: jinja2 (>=3.1.2,<4.0.0)
Requires-Dist: rich (>=13.3.1,<14.0.0)
Requires-Dist: typer (>=0.7.0,<0.8.0)
